DAKimport/DAKimport.py
DAKimport/__init__.py
DAKimport-0.0.5.dist-info/LICENSE
DAKimport-0.0.5.dist-info/METADATA
DAKimport-0.0.5.dist-info/WHEEL
DAKimport-0.0.5.dist-info/top_level.txt
DAKimport-0.0.5.dist-info/RECORD
