Metadata-Version: 2.1
Name: DAKimport
Version: 0.0.5
Summary: convert Designaknit .stp and .pat knitting pattern files into images
Home-page: https://github.com/t0mpr1c3/DAKimport
Author: Tom Price
Author-email: t0mpr1c3@gmail.com
License: UNKNOWN
Platform: UNKNOWN
Classifier: Programming Language :: Python :: 3
Classifier: License :: OSI Approved :: MIT License
Classifier: Operating System :: OS Independent
Requires-Python: >=3.5
License-File: LICENSE
Requires-Dist: numpy (>=1.18.4)
Requires-Dist: Pillow (>=7.1.2)
Requires-Dist: pypng (>=0.0.20)
